{"about.md":"B8xoTJAu","application_aria2.md":"BzYlJ4qD","application_compose.md":"DT3sOsa0","application_douban_tool.md":"CZXpT11x","application_homepage.md":"D6MP3s4A","application_xiaoya.md":"Ca4ohnOB","basic_app.md":"CYxXurgt","basic_bandwidth.md":"BPudvndm","basic_barreltheory.md":"D6GpegNT","basic_bridge_network.md":"ppjCozwp","basic_bt_script.md":"CiyxNCfY","basic_data_safe.md":"DADov1d3","basic_ddns_port_mapping.md":"DrgG8o7D","basic_docker.md":"CTP08dDe","basic_docker_mirrors.md":"ksReeTaF","basic_network.md":"w2WYeIrm","basic_os.md":"DAn0FkXT","basic_pe.md":"Df9-oojx","basic_question.md":"DeP8jFqT","basic_raid_performance.md":"BOGZ2P9I","basic_remote.md":"C7n2UBw2","basic_search.md":"nw-FSen1","basic_smbshare.md":"D7N4rRPO","basic_speedtest.md":"Cn6HnPQP","basic_temperature.md":"C8HUoJZa","basic_transfer_rate.md":"BBCw5w3s","basic_ups.md":"kd43tVSd","basic_wake_on_lan.md":"DeWbwuCA","case_3d_print_case.md":"ClG6bVnM","case_baozang.md":"Nu373mGm","case_fanlong.md":"qZpWrXFT","case_goldenfield.md":"CFtiZjEP","case_jianfang.md":"D3XxR81k","case_jonsbo.md":"BVv9V4Yf","case_minicase.md":"CvAkYohq","case_seaofstars.md":"_G8GF0-7","contact.md":"BxFvHSUF","copyright.md":"BD89RUxU","counselling.md":"CR7V1lSm","diy_after_sales_service.md":"WnEc4seg","diy_process.md":"Dh3OREMR","diy_rustdesk.md":"BrU62Jpv","diy_store.md":"Bcq8FuJd","diy_support.md":"gE9PPosl","diy_system_solution.md":"Cp_3I85h","example.md":"5prKnvo9","feedback.md":"CnYDrtsb","fnos_aria2.md":"Co7AHzWX","fnos_download.md":"DBw43aZQ","fnos_duplicati.md":"DmdLYZYa","fnos_filebrowser.md":"Dg62kjwc","fnos_immich.md":"Cu0Y_CDm","fnos_metube.md":"Dvl_A6Yu","fnos_movie.md":"hJu97Mbs","fnos_onethingcloud.md":"FfAeTLh2","fnos_question.md":"CX0GwzqN","fnos_speedtest.md":"wQ91hq63","fnos_ssh.md":"BN3a-V1X","fnos_syncthing.md":"DmLrXng0","fnos_tailscale.md":"DD0uOOAK","fnos_ups.md":"BY21pdLY","fnos_zerotier.md":"BUYPI4qW","hardware_cpu.md":"ByNeSDXD","hardware_decode.md":"DPBKQrUN","hardware_gpu.md":"G379Y7MA","hardware_harddrive.md":"GO429whn","hardware_memory.md":"B9LBkyUd","hardware_power_consumption.md":"BgsnZpOl","hardware_test.md":"BoaGp-S1","hardware_troubleshooting.md":"5sixRodA","index.md":"BeZpWttz","istoreos_question.md":"CkKvw3uE","link.md":"BEBpmOGC","pve_basic.md":"zKg65jmh","pve_haos.md":"BzIEch_L","pve_istoreos.md":"ka7Qwqwt","pve_passthrough_harddrive.md":"BnxXfzQz","pve_pcie.md":"CwLcbTmI","pve_reset.md":"DsCKMkvk","pve_update_synology.md":"CkjTXk7L","pve_windows.md":"Dpd8i7nE","resource_app.md":"D4ySS_4Z","resource_bt_pt.md":"FUTu_csn","resource_discover.md":"hCmHrLDJ","resource_iso.md":"B6i74c7I","resource_player.md":"BnMU0IGj","resource_search.md":"CrM7mCfC","resource_system_loader.md":"CxIGtQ_n","resource_tools.md":"Bpt_PpJB","reward.md":"qmjqjMr8","start.md":"BsAgWWon","synology_compose_upgrade.md":"wIdt2UXG","synology_emby_decode.md":"DfVpKFq0","synology_find_synology.md":"C1pbFzuF","synology_fnos.md":"DkJhCypw","synology_immich_deploy.md":"VCcj9G9U","synology_install_system.md":"CZOVZfeJ","synology_jellyfin_decode.md":"AeXz3pMw","synology_macvlan.md":"C4FqOGVd","synology_photos.md":"CZZap1zp","synology_qbittorrent.md":"48INqoSo","synology_router.md":"S9NZy21X","synology_setting_loader.md":"CMsiS8tm","synology_ssd_storage.md":"DueuHp7h","synology_ssh.md":"ZNZ1MzAc","synology_storage_pool.md":"BWLCwALs","synology_upgrade.md":"DeVKTgiI","synology_vi.md":"CrYmPZIr","system_design.md":"C2j9k8B4","test.md":"r0bTIJcR","unraid_additional_disk.md":"CIhOKH7O","unraid_app_icon.md":"DcO6ZdHB","unraid_array.md":"CM5wwZve","unraid_bitwarden.md":"raZkgdKh","unraid_clipboard_sync.md":"pE3K-aVQ","unraid_custom_docker_icon.md":"B-5ZpWfp","unraid_deploy_immich.md":"BD2nHfuv","unraid_download_tools.md":"Bta8yoMw","unraid_duplicati.md":"BXQ4tk9b","unraid_filemanager.md":"Dmg3eIW9","unraid_fnos.md":"DcEDCQ2u","unraid_format.md":"DjAw3Nht","unraid_git-lfs.md":"a9QEMRxC","unraid_hamsterbase.md":"4RZpPhrR","unraid_haos.md":"C5hrGuFz","unraid_immich_ai_model.md":"BfF-GLZR","unraid_intel_gpu_setting.md":"DGqcDY8j","unraid_javspider.md":"BPJm0qtR","unraid_jellyfin_harddecode.md":"BbEn-3sF","unraid_jellyfin_play_clouddrive.md":"C3KlXX1J","unraid_planka.md":"BJ0XVCL5","unraid_plugins.md":"COZamZGd","unraid_qbittorrent_webui.md":"gM8HzrDU","unraid_question.md":"BnnU1ZYt","unraid_remote.md":"CBqkCs9m","unraid_reset_array.md":"BpGjpiz4","unraid_router.md":"DPhrZ3Z5","unraid_share_folder.md":"Ds9dgCh_","unraid_speedtest.md":"Dw_GV4Rw","unraid_storage.md":"dPb-mYzE","unraid_tmm.md":"CTJvc_Ry","unraid_unraid_docker_template.md":"DZ4ygY1R","unraid_user_experience.md":"BwFseGzd","unraid_user_share.md":"B8VhZJLI","unraid_windows.md":"D6B6aM7q","unraid_xiaoya.md":"4VZDzHq4"}
